coloraphie-1.0.0.dist-info/licenses/LICENSE
colorfy/__init__.py
colorfy/core.py
coloraphie-1.0.0.dist-info/METADATA
coloraphie-1.0.0.dist-info/WHEEL
coloraphie-1.0.0.dist-info/top_level.txt
coloraphie-1.0.0.dist-info/RECORD
