Metadata-Version: 2.4
Name: coloraphie
Version: 1.0.0
Summary: Простая библиотека для цветного текста в консоли
Author-email: vvoid <plip30392@gmail.com>
License: MIT
Project-URL: Homepage, https://github.com/zqLinkqn/
Requires-Python: >=3.8
License-File: LICENSE
Dynamic: license-file
